lazyimports/__init__.py
lazyimports/__main__.py
hatch_autorun_auto_lazy_imports.pth
auto_lazy_imports-0.4.2.dist-info/METADATA
auto_lazy_imports-0.4.2.dist-info/WHEEL
auto_lazy_imports-0.4.2.dist-info/RECORD
