Metadata-Version: 2.4
Name: auto-lazy-imports
Version: 0.4.2
Summary: A module to enable lazy imports using native python syntax
Project-URL: Repository, https://github.com/hmiladhia/lazyimports
Project-URL: Issues, https://github.com/hmiladhia/lazyimports/issues
Author: Dhia Hmila
License: MIT License
Classifier: Intended Audience :: Developers
Classifier: License :: OSI Approved :: MIT License
Classifier: Programming Language :: Python :: 3
Classifier: Programming Language :: Python :: 3.9
Classifier: Programming Language :: Python :: 3.10
Classifier: Programming Language :: Python :: 3.11
Classifier: Programming Language :: Python :: 3.12
Classifier: Programming Language :: Python :: 3.13
Requires-Python: >=3.9
